digitalhub_core_nefertem/__init__.py
digitalhub_core_nefertem/entities/functions/__init__.py
digitalhub_core_nefertem/entities/functions/spec.py
digitalhub_core_nefertem/entities/tasks/__init__.py
digitalhub_core_nefertem/entities/tasks/spec.py
digitalhub_core_nefertem/runtime/__init__.py
digitalhub_core_nefertem/runtime/runtime.py
digitalhub_core_nefertem-0.0.6.dist-info/LICENSE.txt
digitalhub_core_nefertem-0.0.6.dist-info/METADATA
digitalhub_core_nefertem-0.0.6.dist-info/WHEEL
digitalhub_core_nefertem-0.0.6.dist-info/top_level.txt
digitalhub_core_nefertem-0.0.6.dist-info/RECORD
